PCNN/__init__.py
PCNN/auxiliaries.py
PCNN/classic_model.py
PCNN/flm_model.py
PCNN/general_model.py
PCNN/icm_model.py
PCNN/scm_model.py
PCNN/simulator.py
PCNN/slm_model.py
Pulse_Coupled_Neural_Networks-0.0.2.dist-info/LICENSE.txt
Pulse_Coupled_Neural_Networks-0.0.2.dist-info/METADATA
Pulse_Coupled_Neural_Networks-0.0.2.dist-info/WHEEL
Pulse_Coupled_Neural_Networks-0.0.2.dist-info/top_level.txt
Pulse_Coupled_Neural_Networks-0.0.2.dist-info/RECORD
